README.rst
setup.py
pkgen/__init__.py
pkgen/pkgen.py
pkgen.egg-info/PKG-INFO
pkgen.egg-info/SOURCES.txt
pkgen.egg-info/dependency_links.txt
pkgen.egg-info/not-zip-safe
pkgen.egg-info/top_level.txt