Metadata-Version: 1.0
Name: pkgen
Version: 0.1
Summary: Primary Key Generator Implemented In Python
Home-page: https://github.com/streethacker/pkgen
Author: YUCHI
Author-email: wei.chensh@ele.me
License: UNKNOWN
Platform: UNKNOWN
